{
  "main": {
    "id": "93bb44f5a373d597",
    "type": "split",
    "children": [
      {
        "id": "01b60ea367977649",
        "type": "tabs",
        "children": [
          {
            "id": "5e0db4bb3b1843fd",
            "type": "leaf",
            "state": {
              "type": "markdown",
              "state": {
                "file": "Moral Psychology/Dual Process Theory.md",
                "mode": "source",
                "source": false
              }
            }
          },
          {
            "id": "f0c59a3405269c0b",
            "type": "leaf",
            "state": {
              "type": "markdown",
              "state": {
                "file": "conflict-files-obsidian-git.md",
                "mode": "source",
                "source": false
              }
            }
          }
        ],
        "currentTab": 1
      }
    ],
    "direction": "vertical"
  },
  "left": {
    "id": "051c923febacd79f",
    "type": "split",
    "children": [
      {
        "id": "d76366cbac5c7792",
        "type": "tabs",
        "children": [
          {
            "id": "f70bad8294d50d2c",
            "type": "leaf",
            "state": {
              "type": "file-explorer",
              "state": {
                "sortOrder": "alphabetical"
              }
            }
          },
          {
            "id": "816fd8e8fbe71645",
            "type": "leaf",
            "state": {
              "type": "search",
              "state": {
                "query": "moore",
                "matchingCase": false,
                "explainSearch": false,
                "collapseAll": false,
                "extraContext": false,
                "sortOrder": "alphabetical"
              }
            }
          }
        ]
      }
    ],
    "direction": "horizontal",
    "width": 309.5
    "width": 290.5,
    "collapsed": true
  },
  "right": {
    "id": "01c44d9d44bab086",
    "type": "split",
    "children": [
      {
        "id": "45e4ef752b308e6f",
        "type": "tabs",
        "children": [
          {
            "id": "318f969d1810d63f",
            "type": "leaf",
            "state": {
              "type": "backlink",
              "state": {
                "file": "Moral Psychology/Dual Process Theory.md",
                "collapseAll": false,
                "extraContext": false,
                "sortOrder": "alphabetical",
                "showSearch": false,
                "searchQuery": "",
                "backlinkCollapsed": false,
                "unlinkedCollapsed": true
              }
            }
          },
          {
            "id": "0a0b852c2c8ddb3b",
            "type": "leaf",
            "state": {
              "type": "outgoing-link",
              "state": {
                "file": "Moral Psychology/Dual Process Theory.md",
                "linksCollapsed": false,
                "unlinkedCollapsed": true
              }
            }
          },
          {
            "id": "cf2884f87ac5e121",
            "type": "leaf",
            "state": {
              "type": "outline",
              "state": {
                "file": "Moral Psychology/Dual Process Theory.md"
              }
            }
          },
          {
            "id": "ae6eae0de275e4ac",
            "type": "leaf",
            "state": {
              "type": "git-view",
              "state": {}
            }
          }
        ]
      }
    ],
    "direction": "horizontal",
    "width": 300,
    "collapsed": true
  },
  "left-ribbon": {
    "hiddenItems": {
      "switcher:Open quick switcher": true,
      "command-palette:Open command palette": true
    }
  },
  "active": "5e0db4bb3b1843fd",
  "lastOpenFiles": [
    "Moral Psychology/Well being.md",
    "Moral Psychology/Dual Process Theory.md",
    "Philosophy/Ethics/Why be moral.md",
    "Philosophy/Ethics/Well-being/Well-Being.md",
    "Philosophy/Untitled.md",
    "Philosophy/Untitled 1.md",
    "Philosophy/Ethics/Well-being",
    "Psychology PhD course/Elnglish/Homework/2023 12 30.md",
    "Moral Psychology",
    "Psychology PhD course/Elnglish/Article/Article 13 12 2023.md",
    "Psychology PhD course/Elnglish/Article/Article.md",
    "Psychology PhD course/Philosophy/2023 11 23.md",
    "Life/Ideas.md",
    "Life",
    "IT/SQL/PostgreSQL/Working with tables.md",
    "IT/SQL/PostgreSQL/Working with database.md",
    "IT/SQL/PostgreSQL/Open PostgreSQL promt.md",
    "IT/SQL/PostgreSQL/Installation.md",
    "IT/SQL/MySQL/Working with tables.md",
    "IT/SQL/MySQL/Working with databases.md",
    "IT/SQL/MySQL/Open Mysql Promt.md",
    "IT/SQL/MySQL/Installation.md",
    "IT/SQL/MySQL/Index.md",
    "IT/SQL/MySQL/Create a dump.md",
    "IT/SQL/PostgreSQL",
    "IT/SQL/Normalization.md",
    "IT/SQL/MySQL",
    "IT/SQL/Isolation Levels.md",
    "IT/SQL/ACID.md",
    "IT/SQL",
    "IT/Python/Create new project.md",
    "IT/Python",
    "IT/Nvim/Windows like shortcuts.md",
    "IT/Nvim",
    "IT/Linux/Troubleshooting/Logs",
    "IT/Linux/Internet/Http Servers",
    "Untitled-2023-11-10-1121.png",
    "Pasted image 20231110210358.png",
    "Pasted image 20231110190311.png",
    "Pasted image 20231110135620.png",
    "Pasted image 20231110133406.png",
    "Pasted image 20231106235015.png"
  ]
}